grid/__init__.py
grid/cli/__init__.py
grid/cli/run_dht.py
grid/cli/run_prod_server.sh
grid/cli/run_server.py
grid/client/__init__.py
grid/client/from_pretrained.py
grid/client/inference_session.py
grid/client/lm_head.py
grid/client/ptune.py
grid/client/remote_forward_backward.py
grid/client/remote_generation.py
grid/client/remote_sequential.py
grid/client/routing/__init__.py
grid/client/routing/sequence_info.py
grid/client/routing/sequence_manager.py
grid/client/routing/spending_policy.py
grid/client/sequential_autograd.py
grid/constants.py
grid/data_structures.py
grid/dht_utils.py
grid/models/__init__.py
grid/models/bloom/__init__.py
grid/models/bloom/block.py
grid/models/bloom/config.py
grid/models/bloom/model.py
grid/models/llama/__init__.py
grid/models/llama/block.py
grid/models/llama/config.py
grid/models/llama/model.py
grid/server/__init__.py
grid/server/backend.py
grid/server/block_selection.py
grid/server/block_utils.py
grid/server/from_pretrained.py
grid/server/handler.py
grid/server/memory_cache.py
grid/server/reachability.py
grid/server/server.py
grid/server/task_pool.py
grid/server/task_prioritizer.py
grid/server/throughput.py
grid/utils/__init__.py
grid/utils/asyncio.py
grid/utils/auto_config.py
grid/utils/convert_block.py
grid/utils/disk_cache.py
grid/utils/generation_algorithms.py
grid/utils/generation_constraints.py
grid/utils/hf_auth.py
grid/utils/logging.py
grid/utils/misc.py
grid/utils/peft.py
grid/utils/ping.py
grid/utils/random.py
grid/utils/version.py
the_grid-0.1.0.dist-info/LICENSE
the_grid-0.1.0.dist-info/WHEEL
the_grid-0.1.0.dist-info/METADATA
the_grid-0.1.0.dist-info/RECORD
